planegeometry/__init__.py
planegeometry/algorithms/__init__.py
planegeometry/algorithms/bentleyottmann1.py
planegeometry/algorithms/bentleyottmann2.py
planegeometry/algorithms/closestpair1.py
planegeometry/algorithms/closestpair3.py
planegeometry/algorithms/closestpair4.py
planegeometry/algorithms/geomtools.py
planegeometry/algorithms/horizontalvertical.py
planegeometry/algorithms/shamoshoey1.py
planegeometry/algorithms/shamoshoey2.py
planegeometry/algorithms/tests/__init__.py
planegeometry/algorithms/tests/hv_segments.py
planegeometry/algorithms/tests/hv_segments2.py
planegeometry/algorithms/tests/test_bentleyottmann1.py
planegeometry/algorithms/tests/test_bentleyottmann2.py
planegeometry/algorithms/tests/test_closestpair1.py
planegeometry/algorithms/tests/test_closestpair3.py
planegeometry/algorithms/tests/test_closestpair4.py
planegeometry/algorithms/tests/test_geomtools.py
planegeometry/algorithms/tests/test_horizontalvertical.py
planegeometry/algorithms/tests/test_shamoshoey1.py
planegeometry/algorithms/tests/test_shamoshoey2.py
planegeometry/algorithms/tests/timeit_closestpair.py
planegeometry/algorithms/tests/timeit_furthestpoints.py
planegeometry/algorithms/tests/timeit_intersections.py
planegeometry/algorithms/tests/unit_segments.py
planegeometry/algorithms/tests/unit_segments2.py
planegeometry/hulls/__init__.py
planegeometry/hulls/graham.py
planegeometry/hulls/jarvis.py
planegeometry/hulls/quickhull.py
planegeometry/hulls/tests/__init__.py
planegeometry/hulls/tests/test_graham.py
planegeometry/hulls/tests/test_jarvis.py
planegeometry/hulls/tests/test_quickhull.py
planegeometry/hulls/tests/timeit_hull1.py
planegeometry/hulls/tests/timeit_hull2.py
planegeometry/hulls/tests/timeit_hull3.py
planegeometry/structures/__init__.py
planegeometry/structures/avltree1.py
planegeometry/structures/avltree2.py
planegeometry/structures/circles.py
planegeometry/structures/edges.py
planegeometry/structures/events.py
planegeometry/structures/graphs.py
planegeometry-1.0.3.dist-info/LICENSE
planegeometry-1.0.3.dist-info/METADATA
planegeometry-1.0.3.dist-info/WHEEL
planegeometry-1.0.3.dist-info/top_level.txt
planegeometry-1.0.3.dist-info/RECORD
